README.md
setup.cfg
setup.py
cryptonator_API/__init__.py
cryptonator_API/cryptonator_API.py
cryptonator_API.egg-info/PKG-INFO
cryptonator_API.egg-info/SOURCES.txt
cryptonator_API.egg-info/dependency_links.txt
cryptonator_API.egg-info/not-zip-safe
cryptonator_API.egg-info/top_level.txt