Metadata-Version: 2.1
Name: cryptonator-API
Version: 0.0
Summary: cryptonator_API for https://www.cryptonator.com/
Home-page: UNKNOWN
Author-email: m0rtydisg@gmail.com
License: UNKNOWN
Platform: UNKNOWN
